README.rst
setup.py
django_fence.egg-info/PKG-INFO
django_fence.egg-info/SOURCES.txt
django_fence.egg-info/dependency_links.txt
django_fence.egg-info/top_level.txt
fence/__init__.py
fence/middleware.py
fence/models.py
fence/tests.py
fence/views.py