Metadata-Version: 1.1
Name: django-fence
Version: 0.0.3
Summary: Simple middleware to restrict access to "private beta" sites
Home-page: http://github.com/yourcelf/django-fence
Author: Charlie DeTar
Author-email: cfd@fohn.org
License: MIT
Platform: UNKNOWN
Classifier: Environment :: Web Environment
Classifier: Framework :: Django
Classifier: Intended Audience :: Developers
Classifier: License :: OSI Approved :: BSD License
Classifier: Operating System :: OS Independent
Classifier: Programming Language :: Python
Classifier: Topic :: Internet :: WWW/HTTP
Classifier: Topic :: Internet :: WWW/HTTP :: Dynamic Content
